snakemake_staging/__init__.py
snakemake_staging/config.py
snakemake_staging/git.py
snakemake_staging/rules.py
snakemake_staging/stages.py
snakemake_staging/testing.py
snakemake_staging/utils.py
snakemake_staging/version.py
snakemake_staging/workflow/Snakefile
snakemake_staging/workflow/envs/git.yml
snakemake_staging/workflow/rules/git.smk
snakemake_staging/workflow/rules/noop.smk
snakemake_staging/workflow/rules/stages.smk
snakemake_staging/workflow/rules/zenodo.smk
snakemake_staging/zenodo.py
snakemake_staging-0.0.2.dist-info/LICENSE
snakemake_staging-0.0.2.dist-info/METADATA
snakemake_staging-0.0.2.dist-info/WHEEL
snakemake_staging-0.0.2.dist-info/RECORD
