Metadata-Version: 2.1
Name: snakemake-staging
Version: 0.0.2
Summary: 
Author: Dan Foreman-Mackey
Author-email: foreman.mackey@gmail.com
Requires-Python: >=3.9
Classifier: Programming Language :: Python :: 3
Classifier: Programming Language :: Python :: 3.9
Classifier: Programming Language :: Python :: 3.10
Classifier: Programming Language :: Python :: 3.11
Requires-Dist: requests
Requires-Dist: snakemake
